cloud_data_cockpit/__init__.py
cloud_data_cockpit/aws_utils.py
cloud_data_cockpit/core.py
cloud_data_cockpit/events.py
cloud_data_cockpit/format_handlers.py
cloud_data_cockpit/ui_builder.py
cloud_data_cockpit/data/public_datasets_dict.json
cloud_data_cockpit/data/script.py
cloud_data_cockpit/widgets/custom_components.py
cloud_data_cockpit/widgets/metaspace_widget.py
cloud_data_cockpit/widgets/public_datasets_widget.py
cloud_data_cockpit/widgets/s3_explorer_widget.py
cloud_data_cockpit/widgets/upload_widget.py
cloud_data_cockpit/widgets/styles/custom_styles.css
cloud_data_cockpit-1.0.4.dist-info/licenses/LICENSE
cloud_data_cockpit-1.0.4.dist-info/METADATA
cloud_data_cockpit-1.0.4.dist-info/WHEEL
cloud_data_cockpit-1.0.4.dist-info/top_level.txt
cloud_data_cockpit-1.0.4.dist-info/RECORD
