Metadata-Version: 2.4
Name: cloud-data-cockpit
Version: 1.0.4
Summary: An IPython widget for browsing, benchmarking, and processing S3 datasets.
Home-page: https://github.com/ubenabdelkrim/data_cockpit
Author: Usama Benabdelkrim Zakan
Author-email: Usama Benabdelkrim Zakan <usama.benabdelkrim@urv.cat>
License: MIT
Classifier: Programming Language :: Python :: 3
Classifier: License :: OSI Approved :: MIT License
Classifier: Operating System :: OS Independent
Requires-Python: >=3.10
License-File: LICENSE
Requires-Dist: boto3
Requires-Dist: ipywidgets
Requires-Dist: gql
Requires-Dist: cloud-dataplug
Requires-Dist: ipython
Requires-Dist: requests_toolbelt
Requires-Dist: rasterio
Provides-Extra: geospatial
Requires-Dist: cloud-dataplug[geospatial]; extra == "geospatial"
Requires-Dist: pdal; extra == "geospatial"
Provides-Extra: metabolomics
Requires-Dist: cloud-dataplug[metabolomics]; extra == "metabolomics"
Dynamic: author
Dynamic: home-page
Dynamic: license-file
Dynamic: requires-python
